europa/__init__.py
europa/py.typed
europa/framework/__init__.py
europa/framework/endpoint.py
europa/framework/launcher.py
europa/framework/logger.py
europa/framework/service.py
europa/framework/sockets.py
europa/framework/queues/__init__.py
europa/framework/queues/queue_manager.py
europa/framework/queues/providers/__init__.py
europa/framework/queues/providers/api.py
europa/framework/queues/providers/inmemory_queue.py
europa/framework/queues/providers/postgres_queue.py
europa/framework/queues/providers/rabbitmq_queue.py
europa/framework/queues/providers/redis_queue.py
europa/services/__init__.py
europa/services/sample_service.py
europa/services/sample_service_with_hazelcast.py
europa/services/sample_service_with_websocket.py
europa/services/sample_single_queue_service.py
europa-0.1.9.dist-info/METADATA
europa-0.1.9.dist-info/WHEEL
europa-0.1.9.dist-info/entry_points.txt
europa-0.1.9.dist-info/RECORD
