Metadata-Version: 2.4
Name: europa
Version: 0.1.9
Summary: Add your description here
Requires-Python: >=3.11
Requires-Dist: fastapi>=0.115.12
Requires-Dist: uvicorn>=0.34.0
Requires-Dist: websocket-client>=1.8.0
